nginx_config_lint/cli.py
nginx_config_lint/constants.py
nginx_config_lint/init.py
nginx_config_lint-0.1.1.dist-info/licenses/LICENSE
nginx_config_lint-0.1.1.dist-info/METADATA
nginx_config_lint-0.1.1.dist-info/WHEEL
nginx_config_lint-0.1.1.dist-info/entry_points.txt
nginx_config_lint-0.1.1.dist-info/top_level.txt
nginx_config_lint-0.1.1.dist-info/RECORD
